recpp/__init__.py
recpp/__main__.py
recpp/cli.py
recpp/preprocessor.py
recpp-0.1.0.dist-info/entry_points.txt
recpp-0.1.0.dist-info/WHEEL
recpp-0.1.0.dist-info/METADATA
recpp-0.1.0.dist-info/RECORD
