Metadata-Version: 2.1
Name: recpp
Version: 0.1.0
Summary: 
Author: Andrew Elgert
Author-email: andrew.elgert@gmail.com
Requires-Python: >=3.10,<4.0
Classifier: Programming Language :: Python :: 3
Classifier: Programming Language :: Python :: 3.10
Requires-Dist: pcpp (>=1.30,<2.0)
